{
	"flipX": true,
	"positionOffset": [
		-39,
		353
	],
	"image": "characters/bf",
	"healthIcon": "bf",
	"anims": [
		{
			"prefix": "BF HEY!!",
			"name": "hey",
			"offset": [
				2,
				5
			]
		},
		{
			"prefix": "BF idle dance",
			"name": "idle",
			"offset": [
				0,
				0
			]
		},
		{
			"loop": true,
			"prefix": "BF idle shaking",
			"name": "scared",
			"offset": [
				0,
				1
			]
		},
		{
			"prefix": "BF NOTE DOWN0",
			"name": "singDOWN",
			"offset": [
				-21,
				-52
			]
		},
		{
			"prefix": "BF NOTE DOWN MISS",
			"name": "singDOWNmiss",
			"offset": [
				-21,
				-22
			]
		},
		{
			"prefix": "BF NOTE RIGHT0",
			"name": "singLEFT",
			"offset": [
				45,
				-9
			]
		},
		{
			"prefix": "BF NOTE RIGHT MISS",
			"name": "singLEFTmiss",
			"offset": [
				39,
				19
			]
		},
		{
			"prefix": "BF NOTE LEFT0",
			"name": "singRIGHT",
			"offset": [
				-31,
				-10
			]
		},
		{
			"prefix": "BF NOTE LEFT MISS",
			"name": "singRIGHTmiss",
			"offset": [
				-32,
				16
			]
		},
		{
			"prefix": "BF NOTE UP0",
			"name": "singUP",
			"offset": [
				6,
				30
			]
		},
		{
			"prefix": "BF NOTE UP MISS",
			"name": "singUPmiss",
			"offset": [
				2,
				30
			]
		}
	],
	"cameraOffset": [
		-15,
		-62
	],
	"healthColors": [
		49,
		176,
		209
	]
}